README.md
setup.cfg
setup.py
wsdaProb/Binomialdistribution.py
wsdaProb/Gaussiandistribution.py
wsdaProb/Generaldistribution.py
wsdaProb/__init__.py
wsdaProb.egg-info/PKG-INFO
wsdaProb.egg-info/SOURCES.txt
wsdaProb.egg-info/dependency_links.txt
wsdaProb.egg-info/not-zip-safe
wsdaProb.egg-info/top_level.txt